MANIFEST.in
README.md
setup.py
adi/__init__.py
adi.commons.egg-info/PKG-INFO
adi.commons.egg-info/SOURCES.txt
adi.commons.egg-info/dependency_links.txt
adi.commons.egg-info/entry_points.txt
adi.commons.egg-info/namespace_packages.txt
adi.commons.egg-info/not-zip-safe
adi.commons.egg-info/requires.txt
adi.commons.egg-info/top_level.txt
adi/commons/__init__.py
adi/commons/commons.py
docs/HISTORY.md
docs/INSTALL.txt
docs/LICENSE.GPL
docs/LICENSE.txt