Metadata-Version: 1.1
Name: adi.commons
Version: 0.5
Summary: Some helpers-methods for often repeating and general purposes, to be used of other eggs.
Home-page: https://github.com/ida/adi.commons/
Author: Ida Ebkes
Author-email: contact@ida-ebkes.eu
License: GPL
Platform: UNKNOWN
Classifier: Framework :: Plone
Classifier: Programming Language :: Python
